fs/__init__.py
fs/__init__.pyi
fs/compression.py
fs/io.py
fs/moving.py
fs/parallel.py
fs/paths.py
fs/reading.py
fs/tar.py
fs_tools-0.1.17.dist-info/METADATA
fs_tools-0.1.17.dist-info/WHEEL
fs_tools-0.1.17.dist-info/top_level.txt
fs_tools-0.1.17.dist-info/RECORD
