Metadata-Version: 2.1
Name: fs-tools
Version: 0.1.17
Summary: Simple, exception-free filesystem tools
Author-email: Marcel Claramunt <marcel@moveread.com>
Project-URL: repo, https://github.com/marciclabas/python-storage.git
Requires-Python: >=3.10
Requires-Dist: haskellian===0.3.36
Requires-Dist: typing-extensions
